sqlpyd/__init__.py
sqlpyd/conn.py
sqlpyd/name.py
sqlpyd/tableconfig.py
sqlpyd-0.1.8.dist-info/LICENSE
sqlpyd-0.1.8.dist-info/METADATA
sqlpyd-0.1.8.dist-info/WHEEL
sqlpyd-0.1.8.dist-info/RECORD
