Metadata-Version: 2.1
Name: sqlpyd
Version: 0.1.8
Summary: Validate raw content with pydantic for consumption by sqlite-utils.
Home-page: https://lawsql.com
Author: Marcelino G. Veloso III
Author-email: mars@veloso.one
Requires-Python: >=3.10,<4.0
Classifier: Development Status :: 4 - Beta
Classifier: Framework :: Pydantic
Classifier: Framework :: Pytest
Classifier: Intended Audience :: Legal Industry
Classifier: Programming Language :: Python :: 3
Classifier: Programming Language :: Python :: 3.10
Classifier: Programming Language :: Python :: 3.11
Classifier: Programming Language :: Python :: 3.11
Classifier: Topic :: Text Processing :: General
Classifier: Typing :: Typed
Requires-Dist: pydantic (>=1.10.7,<2.0.0)
Requires-Dist: python-dotenv (>=1.0,<2.0)
Requires-Dist: sqlite-utils (>=3.31,<4.0)
Project-URL: Documentation, https://github.com/justmars/sqlpyd
Project-URL: Repository, https://github.com/justmars/sqlpyd
